sparkypanda/__init__.py
sparkypanda/sparkypanda.py
sparkypandas-0.1.1.dist-info/AUTHORS.rst
sparkypandas-0.1.1.dist-info/LICENSE
sparkypandas-0.1.1.dist-info/METADATA
sparkypandas-0.1.1.dist-info/WHEEL
sparkypandas-0.1.1.dist-info/top_level.txt
sparkypandas-0.1.1.dist-info/RECORD
