Metadata-Version: 2.1
Name: sparkypandas
Version: 0.1.1
Summary: A spark like interface to pandas data frames
Home-page: https://github.com/priamai/sparkypanda
Author: Priam AI
Author-email: paolo@priam.ai
License: Apache Software License 2.0
Keywords: sparkypanda
Platform: UNKNOWN
Classifier: Development Status :: 2 - Pre-Alpha
Classifier: Intended Audience :: Developers
Classifier: License :: OSI Approved :: Apache Software License
Classifier: Natural Language :: English
Classifier: Programming Language :: Python :: 3
Classifier: Programming Language :: Python :: 3.5
Classifier: Programming Language :: Python :: 3.6
Classifier: Programming Language :: Python :: 3.7
Classifier: Programming Language :: Python :: 3.8
Requires-Python: >=3.0, !=3.0.*, !=3.1.*, !=3.2.*, !=3.3.*, !=3.4.*
